pollinations/__init__.py
pollinations/client.py
pollinations/exceptions.py
pollinations/openai_compat.py
pollinations_client-0.1.1.dist-info/licenses/LICENSE
pollinations_client-0.1.1.dist-info/METADATA
pollinations_client-0.1.1.dist-info/WHEEL
pollinations_client-0.1.1.dist-info/top_level.txt
pollinations_client-0.1.1.dist-info/RECORD
