Metadata-Version: 2.4
Name: pollinations-client
Version: 0.1.1
Summary: Python wrapper for Pollinations AI - Free text and image generation APIs
Author: gpt4free
License: MIT
Project-URL: Homepage, https://github.com/gpt4free/pollinations
Project-URL: Repository, https://github.com/gpt4free/pollinations
Project-URL: Issues, https://github.com/gpt4free/pollinations/issues
Keywords: ai,pollinations,image-generation,text-generation,free-api,gpt4free
Classifier: Development Status :: 3 - Alpha
Classifier: Intended Audience :: Developers
Classifier: Topic :: Software Development :: Libraries :: Python Modules
Classifier: License :: OSI Approved :: MIT License
Classifier: Programming Language :: Python :: 3
Classifier: Programming Language :: Python :: 3.7
Classifier: Programming Language :: Python :: 3.8
Classifier: Programming Language :: Python :: 3.9
Classifier: Programming Language :: Python :: 3.10
Classifier: Programming Language :: Python :: 3.11
Classifier: Programming Language :: Python :: 3.12
Requires-Python: >=3.7
License-File: LICENSE
Requires-Dist: requests>=2.31.0
Dynamic: license-file
